<?xml version="1.0" encoding="UTF-8"?>
<odoo>
    <data>
        <record id="action_employee_program" model="ir.actions.act_window">
            <field name="name">employee</field>
            <field name="type">ir.actions.act_window</field>
            <field name="res_model">hr.employee</field>
            <field name="view_mode">tree,form</field>
            <field name="help" type="html">
               <p class="oe_view_nocontent_create">
                    Add a new employee
                </p>
                <p>
                    With just a quick glance on the Odoo employee screen, you
                    can easily find all the information you need for each person;
                    contact data, job position, availability, etc.
                </p>
            </field>
        </record>


    </data>
</odoo>
